pydov/__init__.py
pydov/search/__init__.py
pydov/search/abstract.py
pydov/search/bodemclassificatie.py
pydov/search/bodemdiepteinterval.py
pydov/search/bodemlocatie.py
pydov/search/bodemmonster.py
pydov/search/bodemobservatie.py
pydov/search/bodemsite.py
pydov/search/boring.py
pydov/search/generic.py
pydov/search/grondmonster.py
pydov/search/grondwaterfilter.py
pydov/search/grondwatermonster.py
pydov/search/grondwatervergunning.py
pydov/search/interpretaties.py
pydov/search/sondering.py
pydov/types/__init__.py
pydov/types/abstract.py
pydov/types/bodemclassificatie.py
pydov/types/bodemdiepteinterval.py
pydov/types/bodemlocatie.py
pydov/types/bodemmonster.py
pydov/types/bodemobservatie.py
pydov/types/bodemsite.py
pydov/types/boring.py
pydov/types/fields.py
pydov/types/generic.py
pydov/types/grondmonster.py
pydov/types/grondwaterfilter.py
pydov/types/grondwatermonster.py
pydov/types/grondwatervergunning.py
pydov/types/interpretaties.py
pydov/types/ligging.py
pydov/types/sondering.py
pydov/util/__init__.py
pydov/util/caching.py
pydov/util/dovutil.py
pydov/util/errors.py
pydov/util/hooks.py
pydov/util/location.py
pydov/util/net.py
pydov/util/owsutil.py
pydov/util/query.py
pydov-3.3.1.dist-info/AUTHORS.rst
pydov-3.3.1.dist-info/LICENSE
pydov-3.3.1.dist-info/METADATA
pydov-3.3.1.dist-info/WHEEL
pydov-3.3.1.dist-info/top_level.txt
pydov-3.3.1.dist-info/RECORD
