Metadata-Version: 2.1
Name: pydov
Version: 3.3.1
Summary: A Python package to download data from Databank Ondergrond Vlaanderen (DOV).
Home-page: https://github.com/DOV-Vlaanderen/pydov
Author: DOV-Vlaanderen
Author-email: dov@vlaanderen.be
License: MIT license
Keywords: pydov
Classifier: Development Status :: 5 - Production/Stable
Classifier: Intended Audience :: Developers
Classifier: Intended Audience :: Science/Research
Classifier: License :: OSI Approved :: MIT License
Classifier: Natural Language :: English
Classifier: Natural Language :: Dutch
Classifier: Programming Language :: Python :: 3
Classifier: Programming Language :: Python :: 3.9
Classifier: Programming Language :: Python :: 3.10
Classifier: Programming Language :: Python :: 3.11
Classifier: Programming Language :: Python :: 3.12
Classifier: Programming Language :: Python :: 3.13
Classifier: Topic :: Scientific/Engineering
License-File: LICENSE
License-File: AUTHORS.rst
Requires-Dist: owslib
Requires-Dist: pandas
Requires-Dist: numpy
Requires-Dist: requests
Provides-Extra: devs
Requires-Dist: pip; extra == "devs"
Requires-Dist: bumpversion; extra == "devs"
Requires-Dist: wheel; extra == "devs"
Requires-Dist: watchdog; extra == "devs"
Requires-Dist: flake8; extra == "devs"
Requires-Dist: tox; extra == "devs"
Requires-Dist: coverage; extra == "devs"
Requires-Dist: cryptography; extra == "devs"
Requires-Dist: PyYAML; extra == "devs"
Requires-Dist: pytest; extra == "devs"
Requires-Dist: pytest-runner; extra == "devs"
Requires-Dist: pytest-cov; extra == "devs"
Requires-Dist: Sphinx<8.2,>3; extra == "devs"
Requires-Dist: sphinx-rtd-theme>1; extra == "devs"
Requires-Dist: nbsphinx; extra == "devs"
Requires-Dist: numpydoc; extra == "devs"
Requires-Dist: flask; extra == "devs"
Provides-Extra: docs
Requires-Dist: ipython; extra == "docs"
Requires-Dist: jupyter-client; extra == "docs"
Requires-Dist: ipykernel; extra == "docs"
Requires-Dist: folium; extra == "docs"
Requires-Dist: pyproj; extra == "docs"
Requires-Dist: matplotlib; extra == "docs"
Provides-Extra: geom
Requires-Dist: fiona; extra == "geom"
Requires-Dist: geopandas; extra == "geom"
Requires-Dist: pygml; extra == "geom"
Requires-Dist: shapely; extra == "geom"
Provides-Extra: proxy
Requires-Dist: pypac; extra == "proxy"
Provides-Extra: vectorfile
Requires-Dist: fiona; extra == "vectorfile"
Requires-Dist: geopandas; extra == "vectorfile"
Requires-Dist: pygml; extra == "vectorfile"
Requires-Dist: shapely; extra == "vectorfile"
